Workbook

Sheet Hypothèses
A1: Modèle financier PV — Hypothèses
A2: Légende : cellules en BLEU = à modifier (hypothèses) · JAUNE = paramètres clés · NOIR = calculées automatiquement.
A4: Paramètre | B4: Valeur | C4: Unité
A5: Productible spécifique (Abidjan) | B5: 1400 | C5: kWh/kWc/an
A6: Dégradation annuelle des modules | B6: 0.007 | C6: /an
A7: Puissance par panneau | B7: 500 | C7: Wc
A8: Surface par kWc | B8: 6.5 | C8: m²/kWc
A9: Tarif électricité initial | B9: 80 | C9: FCFA/kWh
A10: Inflation du tarif électricité | B10: 0.03 | C10: /an
A11: O&M annuel (% du CAPEX) | B11: 0.015 | C11: % CAPEX
A12: Durée d'analyse | B12: 25 | C12: ans
A13: Taux d'actualisation (VAN) | B13: 0.08 | C13: /an
A15: Paramètres par configuration | B15: B1 · Injection directe | C15: B2 · Hybride (batterie) | D15: B3 · Sur-mesure
A16: Coût unitaire (FCFA/kWc) | B16: 700000 | C16: 1500000 | D16: 1100000
A17: Taux d'autoconsommation | B17: 0.65 | C17: 0.9 | D17: 0.8
A18: Remplacement onduleur an 12 (% CAPEX) | B18: 0.08 | C18: 0.08 | D18: 0.08
A19: Remplacement batterie an 10 (% CAPEX) | B19: 0 | C19: 0.3 | D19: 0.15
A21: Sources : voir docs/etude-photovoltaique-abidjan.md et docs/business-plan.md. Coûts et tarif à confirmer par devis fournisseurs / factures CIE.

Sheet Cas client
A1: Cas client — dimensionnement à partir de la facture
A2: Renseignez les 3 cellules jaunes ci-dessous ; le reste se calcule tout seul.
A4: Données client (à remplir) | B4: Valeur | C4: Unité
A5: Facture mensuelle moyenne | B5: 45000 | C5: FCFA/mois
A6: Tarif électricité appliqué | B6: =Hypothèses!$B$9 | C6: FCFA/kWh
A7: Taux de couverture solaire visé | B7: 0.8 | C7: % conso
A9: Dimensionnement (calculé)
A10: Consommation mensuelle | B10: =B5/B6 | C10: kWh/mois
A11: Consommation annuelle | B11: =B10*12 | C11: kWh/an
A12: Consommation à couvrir | B12: =B11*B7 | C12: kWh/an
A13: Puissance crête recommandée | B13: =B12/Hypothèses!$B$5 | C13: kWc
A14: Nombre de panneaux | B14: =ROUNDUP(B13*1000/Hypothèses!$B$7,0) | C14: panneaux
A15: Surface de toiture estimée | B15: =B13*Hypothèses!$B$8 | C15: m²

Sheet Comparatif configs
A1: Comparatif des 3 configurations
A2: Même puissance (depuis « Cas client ») comparée sur les 3 architectures.
A4: Indicateur | B4: B1 · Injection | C4: B2 · Hybride | D4: B3 · Sur-mesure
A5: Puissance (kWc) | B5: ='Cas client'!$B$13 | C5: ='Cas client'!$B$13 | D5: ='Cas client'!$B$13
A6: CAPEX (investissement) | B6: ='Cas client'!$B$13*Hypothèses!$B$16 | C6: ='Cas client'!$B$13*Hypothèses!$C$16 | D6: ='Cas client'!$B$13*Hypothèses!$D$16
A7: Production année 1 | B7: ='Cas client'!$B$13*Hypothèses!$B$5 | C7: ='Cas client'!$B$13*Hypothèses!$B$5 | D7: ='Cas client'!$B$13*Hypothèses!$B$5
A8: Énergie autoconsommée an 1 | B8: =MIN('Cas client'!$B$13*Hypothèses!$B$5*Hypothèses!$B$17,'Cas client'!$B$11) | C8: =MIN('Cas client'!$B$13*Hypothèses!$B$5*Hypothèses!$C$17,'Cas client'!$B$11) | D8: =MIN('Cas client'!$B$13*Hypothèses!$B$5*Hypothèses!$D$17,'Cas client'!$B$11)
A9: Économie brute an 1 | B9: =MIN('Cas client'!$B$13*Hypothèses!$B$5*Hypothèses!$B$17,'Cas client'!$B$11)*'Cas client'!$B$6 | C9: =MIN('Cas client'!$B$13*Hypothèses!$B$5*Hypothèses!$C$17,'Cas client'!$B$11)*'Cas client'!$B$6 | D9: =MIN('Cas client'!$B$13*Hypothèses!$B$5*Hypothèses!$D$17,'Cas client'!$B$11)*'Cas client'!$B$6
A10: O&M an 1 | B10: ='Cas client'!$B$13*Hypothèses!$B$16*Hypothèses!$B$11 | C10: ='Cas client'!$B$13*Hypothèses!$C$16*Hypothèses!$B$11 | D10: ='Cas client'!$B$13*Hypothèses!$D$16*Hypothèses!$B$11
A11: Économie nette an 1 | B11: =B9-B10 | C11: =C9-C10 | D11: =D9-D10
A12: Payback brut (années) | B12: =IFERROR(B6/B11,"n/a") | C12: =IFERROR(C6/C11,"n/a") | D12: =IFERROR(D6/D11,"n/a")
A13: VAN 25 ans (actualisée) | B13: ='Cash-flow B1'!$H$3 | C13: ='Cash-flow B2'!$H$3 | D13: ='Cash-flow B3'!$H$3
A14: Flux cumulé à 25 ans | B14: ='Cash-flow B1'!$I$38 | C14: ='Cash-flow B2'!$I$38 | D14: ='Cash-flow B3'!$I$38
A16: Lecture : B1 = meilleur payback (pas de batterie). B2 = confort/nuit (clim) mais retour plus long. VAN positive = projet créateur de valeur sur 25 ans.

Sheet Cash-flow B1
A1: Cash-flow 25 ans — B1 · Injection directe (sans batterie)
A3: Puissance | B3: ='Cas client'!$B$13 | D3: Conso annuelle | E3: ='Cas client'!$B$11 | G3: VAN (25 ans) | H3: =NPV(Hypothèses!$B$13,H14:H38)+H13
A4: CAPEX | B4: =B3*Hypothèses!$B$16 | D4: Taux autoconso. | E4: =Hypothèses!$B$17 | G4: Année de rentabilité | H4: =IF(MIN(J13:J38)>Hypothèses!$B$12,">25 ans",MIN(J13:J38))
A12: Année | B12: Production (kWh) | C12: Tarif (FCFA/kWh) | D12: Autoconso. (kWh) | E12: Économie brute | F12: O&M | G12: Remplacements | H12: Flux net | I12: Flux cumulé
A13: 0 | B13: 0 | C13: 0 | D13: 0 | E13: 0 | F13: 0 | G13: 0 | H13: =-$B$4 | I13: =H13 | J13: =IF(I13>=0,A13,9999)
A14: 1 | B14: =$B$3*Hypothèses!$B$5*(1-Hypothèses!$B$6)^(A14-1) | C14: =Hypothèses!$B$9*(1+Hypothèses!$B$10)^(A14-1) | D14: =MIN(B14*$E$4,$E$3) | E14: =D14*C14 | F14: =$B$4*Hypothèses!$B$11 | G14: =IF(A14=10,$B$4*Hypothèses!$B$19,0)+IF(A14=12,$B$4*Hypothèses!$B$18,0) | H14: =E14-F14-G14 | I14: =I13+H14 | J14: =IF(I14>=0,A14,9999)
A15: 2 | B15: =$B$3*Hypothèses!$B$5*(1-Hypothèses!$B$6)^(A15-1) | C15: =Hypothèses!$B$9*(1+Hypothèses!$B$10)^(A15-1) | D15: =MIN(B15*$E$4,$E$3) | E15: =D15*C15 | F15: =$B$4*Hypothèses!$B$11 | G15: =IF(A15=10,$B$4*Hypothèses!$B$19,0)+IF(A15=12,$B$4*Hypothèses!$B$18,0) | H15: =E15-F15-G15 | I15: =I14+H15 | J15: =IF(I15>=0,A15,9999)
A16: 3 | B16: =$B$3*Hypothèses!$B$5*(1-Hypothèses!$B$6)^(A16-1) | C16: =Hypothèses!$B$9*(1+Hypothèses!$B$10)^(A16-1) | D16: =MIN(B16*$E$4,$E$3) | E16: =D16*C16 | F16: =$B$4*Hypothèses!$B$11 | G16: =IF(A16=10,$B$4*Hypothèses!$B$19,0)+IF(A16=12,$B$4*Hypothèses!$B$18,0) | H16: =E16-F16-G16 | I16: =I15+H16 | J16: =IF(I16>=0,A16,9999)
A17: 4 | B17: =$B$3*Hypothèses!$B$5*(1-Hypothèses!$B$6)^(A17-1) | C17: =Hypothèses!$B$9*(1+Hypothèses!$B$10)^(A17-1) | D17: =MIN(B17*$E$4,$E$3) | E17: =D17*C17 | F17: =$B$4*Hypothèses!$B$11 | G17: =IF(A17=10,$B$4*Hypothèses!$B$19,0)+IF(A17=12,$B$4*Hypothèses!$B$18,0) | H17: =E17-F17-G17 | I17: =I16+H17 | J17: =IF(I17>=0,A17,9999)
A18: 5 | B18: =$B$3*Hypothèses!$B$5*(1-Hypothèses!$B$6)^(A18-1) | C18: =Hypothèses!$B$9*(1+Hypothèses!$B$10)^(A18-1) | D18: =MIN(B18*$E$4,$E$3) | E18: =D18*C18 | F18: =$B$4*Hypothèses!$B$11 | G18: =IF(A18=10,$B$4*Hypothèses!$B$19,0)+IF(A18=12,$B$4*Hypothèses!$B$18,0) | H18: =E18-F18-G18 | I18: =I17+H18 | J18: =IF(I18>=0,A18,9999)
A19: 6 | B19: =$B$3*Hypothèses!$B$5*(1-Hypothèses!$B$6)^(A19-1) | C19: =Hypothèses!$B$9*(1+Hypothèses!$B$10)^(A19-1) | D19: =MIN(B19*$E$4,$E$3) | E19: =D19*C19 | F19: =$B$4*Hypothèses!$B$11 | G19: =IF(A19=10,$B$4*Hypothèses!$B$19,0)+IF(A19=12,$B$4*Hypothèses!$B$18,0) | H19: =E19-F19-G19 | I19: =I18+H19 | J19: =IF(I19>=0,A19,9999)
A20: 7 | B20: =$B$3*Hypothèses!$B$5*(1-Hypothèses!$B$6)^(A20-1) | C20: =Hypothèses!$B$9*(1+Hypothèses!$B$10)^(A20-1) | D20: =MIN(B20*$E$4,$E$3) | E20: =D20*C20 | F20: =$B$4*Hypothèses!$B$11 | G20: =IF(A20=10,$B$4*Hypothèses!$B$19,0)+IF(A20=12,$B$4*Hypothèses!$B$18,0) | H20: =E20-F20-G20 | I20: =I19+H20 | J20: =IF(I20>=0,A20,9999)
A21: 8 | B21: =$B$3*Hypothèses!$B$5*(1-Hypothèses!$B$6)^(A21-1) | C21: =Hypothèses!$B$9*(1+Hypothèses!$B$10)^(A21-1) | D21: =MIN(B21*$E$4,$E$3) | E21: =D21*C21 | F21: =$B$4*Hypothèses!$B$11 | G21: =IF(A21=10,$B$4*Hypothèses!$B$19,0)+IF(A21=12,$B$4*Hypothèses!$B$18,0) | H21: =E21-F21-G21 | I21: =I20+H21 | J21: =IF(I21>=0,A21,9999)
A22: 9 | B22: =$B$3*Hypothèses!$B$5*(1-Hypothèses!$B$6)^(A22-1) | C22: =Hypothèses!$B$9*(1+Hypothèses!$B$10)^(A22-1) | D22: =MIN(B22*$E$4,$E$3) | E22: =D22*C22 | F22: =$B$4*Hypothèses!$B$11 | G22: =IF(A22=10,$B$4*Hypothèses!$B$19,0)+IF(A22=12,$B$4*Hypothèses!$B$18,0) | H22: =E22-F22-G22 | I22: =I21+H22 | J22: =IF(I22>=0,A22,9999)
A23: 10 | B23: =$B$3*Hypothèses!$B$5*(1-Hypothèses!$B$6)^(A23-1) | C23: =Hypothèses!$B$9*(1+Hypothèses!$B$10)^(A23-1) | D23: =MIN(B23*$E$4,$E$3) | E23: =D23*C23 | F23: =$B$4*Hypothèses!$B$11 | G23: =IF(A23=10,$B$4*Hypothèses!$B$19,0)+IF(A23=12,$B$4*Hypothèses!$B$18,0) | H23: =E23-F23-G23 | I23: =I22+H23 | J23: =IF(I23>=0,A23,9999)
A24: 11 | B24: =$B$3*Hypothèses!$B$5*(1-Hypothèses!$B$6)^(A24-1) | C24: =Hypothèses!$B$9*(1+Hypothèses!$B$10)^(A24-1) | D24: =MIN(B24*$E$4,$E$3) | E24: =D24*C24 | F24: =$B$4*Hypothèses!$B$11 | G24: =IF(A24=10,$B$4*Hypothèses!$B$19,0)+IF(A24=12,$B$4*Hypothèses!$B$18,0) | H24: =E24-F24-G24 | I24: =I23+H24 | J24: =IF(I24>=0,A24,9999)
A25: 12 | B25: =$B$3*Hypothèses!$B$5*(1-Hypothèses!$B$6)^(A25-1) | C25: =Hypothèses!$B$9*(1+Hypothèses!$B$10)^(A25-1) | D25: =MIN(B25*$E$4,$E$3) | E25: =D25*C25 | F25: =$B$4*Hypothèses!$B$11 | G25: =IF(A25=10,$B$4*Hypothèses!$B$19,0)+IF(A25=12,$B$4*Hypothèses!$B$18,0) | H25: =E25-F25-G25 | I25: =I24+H25 | J25: =IF(I25>=0,A25,9999)
... A38: 25 | B38: =$B$3*Hypothèses!$B$5*(1-Hypothèses!$B$6)^(A38-1) | C38: =Hypothèses!$B$9*(1+Hypothèses!$B$10)^(A38-1) | D38: =MIN(B38*$E$4,$E$3) | E38: =D38*C38 | F38: =$B$4*Hypothèses!$B$11 | G38: =IF(A38=10,$B$4*Hypothèses!$B$19,0)+IF(A38=12,$B$4*Hypothèses!$B$18,0) | H38: =E38-F38-G38 | I38: =I37+H38 | J38: =IF(I38>=0,A38,9999)

Sheet Cash-flow B2
A1: Cash-flow 25 ans — B2 · Hybride (avec batterie)
A3: Puissance | B3: ='Cas client'!$B$13 | D3: Conso annuelle | E3: ='Cas client'!$B$11 | G3: VAN (25 ans) | H3: =NPV(Hypothèses!$B$13,H14:H38)+H13
A4: CAPEX | B4: =B3*Hypothèses!$C$16 | D4: Taux autoconso. | E4: =Hypothèses!$C$17 | G4: Année de rentabilité | H4: =IF(MIN(J13:J38)>Hypothèses!$B$12,">25 ans",MIN(J13:J38))
A12: Année | B12: Production (kWh) | C12: Tarif (FCFA/kWh) | D12: Autoconso. (kWh) | E12: Économie brute | F12: O&M | G12: Remplacements | H12: Flux net | I12: Flux cumulé
A13: 0 | B13: 0 | C13: 0 | D13: 0 | E13: 0 | F13: 0 | G13: 0 | H13: =-$B$4 | I13: =H13 | J13: =IF(I13>=0,A13,9999)
A14: 1 | B14: =$B$3*Hypothèses!$B$5*(1-Hypothèses!$B$6)^(A14-1) | C14: =Hypothèses!$B$9*(1+Hypothèses!$B$10)^(A14-1) | D14: =MIN(B14*$E$4,$E$3) | E14: =D14*C14 | F14: =$B$4*Hypothèses!$B$11 | G14: =IF(A14=10,$B$4*Hypothèses!$C$19,0)+IF(A14=12,$B$4*Hypothèses!$C$18,0) | H14: =E14-F14-G14 | I14: =I13+H14 | J14: =IF(I14>=0,A14,9999)
A15: 2 | B15: =$B$3*Hypothèses!$B$5*(1-Hypothèses!$B$6)^(A15-1) | C15: =Hypothèses!$B$9*(1+Hypothèses!$B$10)^(A15-1) | D15: =MIN(B15*$E$4,$E$3) | E15: =D15*C15 | F15: =$B$4*Hypothèses!$B$11 | G15: =IF(A15=10,$B$4*Hypothèses!$C$19,0)+IF(A15=12,$B$4*Hypothèses!$C$18,0) | H15: =E15-F15-G15 | I15: =I14+H15 | J15: =IF(I15>=0,A15,9999)
A16: 3 | B16: =$B$3*Hypothèses!$B$5*(1-Hypothèses!$B$6)^(A16-1) | C16: =Hypothèses!$B$9*(1+Hypothèses!$B$10)^(A16-1) | D16: =MIN(B16*$E$4,$E$3) | E16: =D16*C16 | F16: =$B$4*Hypothèses!$B$11 | G16: =IF(A16=10,$B$4*Hypothèses!$C$19,0)+IF(A16=12,$B$4*Hypothèses!$C$18,0) | H16: =E16-F16-G16 | I16: =I15+H16 | J16: =IF(I16>=0,A16,9999)
A17: 4 | B17: =$B$3*Hypothèses!$B$5*(1-Hypothèses!$B$6)^(A17-1) | C17: =Hypothèses!$B$9*(1+Hypothèses!$B$10)^(A17-1) | D17: =MIN(B17*$E$4,$E$3) | E17: =D17*C17 | F17: =$B$4*Hypothèses!$B$11 | G17: =IF(A17=10,$B$4*Hypothèses!$C$19,0)+IF(A17=12,$B$4*Hypothèses!$C$18,0) | H17: =E17-F17-G17 | I17: =I16+H17 | J17: =IF(I17>=0,A17,9999)
A18: 5 | B18: =$B$3*Hypothèses!$B$5*(1-Hypothèses!$B$6)^(A18-1) | C18: =Hypothèses!$B$9*(1+Hypothèses!$B$10)^(A18-1) | D18: =MIN(B18*$E$4,$E$3) | E18: =D18*C18 | F18: =$B$4*Hypothèses!$B$11 | G18: =IF(A18=10,$B$4*Hypothèses!$C$19,0)+IF(A18=12,$B$4*Hypothèses!$C$18,0) | H18: =E18-F18-G18 | I18: =I17+H18 | J18: =IF(I18>=0,A18,9999)
A19: 6 | B19: =$B$3*Hypothèses!$B$5*(1-Hypothèses!$B$6)^(A19-1) | C19: =Hypothèses!$B$9*(1+Hypothèses!$B$10)^(A19-1) | D19: =MIN(B19*$E$4,$E$3) | E19: =D19*C19 | F19: =$B$4*Hypothèses!$B$11 | G19: =IF(A19=10,$B$4*Hypothèses!$C$19,0)+IF(A19=12,$B$4*Hypothèses!$C$18,0) | H19: =E19-F19-G19 | I19: =I18+H19 | J19: =IF(I19>=0,A19,9999)
A20: 7 | B20: =$B$3*Hypothèses!$B$5*(1-Hypothèses!$B$6)^(A20-1) | C20: =Hypothèses!$B$9*(1+Hypothèses!$B$10)^(A20-1) | D20: =MIN(B20*$E$4,$E$3) | E20: =D20*C20 | F20: =$B$4*Hypothèses!$B$11 | G20: =IF(A20=10,$B$4*Hypothèses!$C$19,0)+IF(A20=12,$B$4*Hypothèses!$C$18,0) | H20: =E20-F20-G20 | I20: =I19+H20 | J20: =IF(I20>=0,A20,9999)
A21: 8 | B21: =$B$3*Hypothèses!$B$5*(1-Hypothèses!$B$6)^(A21-1) | C21: =Hypothèses!$B$9*(1+Hypothèses!$B$10)^(A21-1) | D21: =MIN(B21*$E$4,$E$3) | E21: =D21*C21 | F21: =$B$4*Hypothèses!$B$11 | G21: =IF(A21=10,$B$4*Hypothèses!$C$19,0)+IF(A21=12,$B$4*Hypothèses!$C$18,0) | H21: =E21-F21-G21 | I21: =I20+H21 | J21: =IF(I21>=0,A21,9999)
A22: 9 | B22: =$B$3*Hypothèses!$B$5*(1-Hypothèses!$B$6)^(A22-1) | C22: =Hypothèses!$B$9*(1+Hypothèses!$B$10)^(A22-1) | D22: =MIN(B22*$E$4,$E$3) | E22: =D22*C22 | F22: =$B$4*Hypothèses!$B$11 | G22: =IF(A22=10,$B$4*Hypothèses!$C$19,0)+IF(A22=12,$B$4*Hypothèses!$C$18,0) | H22: =E22-F22-G22 | I22: =I21+H22 | J22: =IF(I22>=0,A22,9999)
A23: 10 | B23: =$B$3*Hypothèses!$B$5*(1-Hypothèses!$B$6)^(A23-1) | C23: =Hypothèses!$B$9*(1+Hypothèses!$B$10)^(A23-1) | D23: =MIN(B23*$E$4,$E$3) | E23: =D23*C23 | F23: =$B$4*Hypothèses!$B$11 | G23: =IF(A23=10,$B$4*Hypothèses!$C$19,0)+IF(A23=12,$B$4*Hypothèses!$C$18,0) | H23: =E23-F23-G23 | I23: =I22+H23 | J23: =IF(I23>=0,A23,9999)
A24: 11 | B24: =$B$3*Hypothèses!$B$5*(1-Hypothèses!$B$6)^(A24-1) | C24: =Hypothèses!$B$9*(1+Hypothèses!$B$10)^(A24-1) | D24: =MIN(B24*$E$4,$E$3) | E24: =D24*C24 | F24: =$B$4*Hypothèses!$B$11 | G24: =IF(A24=10,$B$4*Hypothèses!$C$19,0)+IF(A24=12,$B$4*Hypothèses!$C$18,0) | H24: =E24-F24-G24 | I24: =I23+H24 | J24: =IF(I24>=0,A24,9999)
A25: 12 | B25: =$B$3*Hypothèses!$B$5*(1-Hypothèses!$B$6)^(A25-1) | C25: =Hypothèses!$B$9*(1+Hypothèses!$B$10)^(A25-1) | D25: =MIN(B25*$E$4,$E$3) | E25: =D25*C25 | F25: =$B$4*Hypothèses!$B$11 | G25: =IF(A25=10,$B$4*Hypothèses!$C$19,0)+IF(A25=12,$B$4*Hypothèses!$C$18,0) | H25: =E25-F25-G25 | I25: =I24+H25 | J25: =IF(I25>=0,A25,9999)
... A38: 25 | B38: =$B$3*Hypothèses!$B$5*(1-Hypothèses!$B$6)^(A38-1) | C38: =Hypothèses!$B$9*(1+Hypothèses!$B$10)^(A38-1) | D38: =MIN(B38*$E$4,$E$3) | E38: =D38*C38 | F38: =$B$4*Hypothèses!$B$11 | G38: =IF(A38=10,$B$4*Hypothèses!$C$19,0)+IF(A38=12,$B$4*Hypothèses!$C$18,0) | H38: =E38-F38-G38 | I38: =I37+H38 | J38: =IF(I38>=0,A38,9999)

Sheet Cash-flow B3
A1: Cash-flow 25 ans — B3 · Sur-mesure
A3: Puissance | B3: ='Cas client'!$B$13 | D3: Conso annuelle | E3: ='Cas client'!$B$11 | G3: VAN (25 ans) | H3: =NPV(Hypothèses!$B$13,H14:H38)+H13
A4: CAPEX | B4: =B3*Hypothèses!$D$16 | D4: Taux autoconso. | E4: =Hypothèses!$D$17 | G4: Année de rentabilité | H4: =IF(MIN(J13:J38)>Hypothèses!$B$12,">25 ans",MIN(J13:J38))
A12: Année | B12: Production (kWh) | C12: Tarif (FCFA/kWh) | D12: Autoconso. (kWh) | E12: Économie brute | F12: O&M | G12: Remplacements | H12: Flux net | I12: Flux cumulé
A13: 0 | B13: 0 | C13: 0 | D13: 0 | E13: 0 | F13: 0 | G13: 0 | H13: =-$B$4 | I13: =H13 | J13: =IF(I13>=0,A13,9999)
A14: 1 | B14: =$B$3*Hypothèses!$B$5*(1-Hypothèses!$B$6)^(A14-1) | C14: =Hypothèses!$B$9*(1+Hypothèses!$B$10)^(A14-1) | D14: =MIN(B14*$E$4,$E$3) | E14: =D14*C14 | F14: =$B$4*Hypothèses!$B$11 | G14: =IF(A14=10,$B$4*Hypothèses!$D$19,0)+IF(A14=12,$B$4*Hypothèses!$D$18,0) | H14: =E14-F14-G14 | I14: =I13+H14 | J14: =IF(I14>=0,A14,9999)
A15: 2 | B15: =$B$3*Hypothèses!$B$5*(1-Hypothèses!$B$6)^(A15-1) | C15: =Hypothèses!$B$9*(1+Hypothèses!$B$10)^(A15-1) | D15: =MIN(B15*$E$4,$E$3) | E15: =D15*C15 | F15: =$B$4*Hypothèses!$B$11 | G15: =IF(A15=10,$B$4*Hypothèses!$D$19,0)+IF(A15=12,$B$4*Hypothèses!$D$18,0) | H15: =E15-F15-G15 | I15: =I14+H15 | J15: =IF(I15>=0,A15,9999)
A16: 3 | B16: =$B$3*Hypothèses!$B$5*(1-Hypothèses!$B$6)^(A16-1) | C16: =Hypothèses!$B$9*(1+Hypothèses!$B$10)^(A16-1) | D16: =MIN(B16*$E$4,$E$3) | E16: =D16*C16 | F16: =$B$4*Hypothèses!$B$11 | G16: =IF(A16=10,$B$4*Hypothèses!$D$19,0)+IF(A16=12,$B$4*Hypothèses!$D$18,0) | H16: =E16-F16-G16 | I16: =I15+H16 | J16: =IF(I16>=0,A16,9999)
A17: 4 | B17: =$B$3*Hypothèses!$B$5*(1-Hypothèses!$B$6)^(A17-1) | C17: =Hypothèses!$B$9*(1+Hypothèses!$B$10)^(A17-1) | D17: =MIN(B17*$E$4,$E$3) | E17: =D17*C17 | F17: =$B$4*Hypothèses!$B$11 | G17: =IF(A17=10,$B$4*Hypothèses!$D$19,0)+IF(A17=12,$B$4*Hypothèses!$D$18,0) | H17: =E17-F17-G17 | I17: =I16+H17 | J17: =IF(I17>=0,A17,9999)
A18: 5 | B18: =$B$3*Hypothèses!$B$5*(1-Hypothèses!$B$6)^(A18-1) | C18: =Hypothèses!$B$9*(1+Hypothèses!$B$10)^(A18-1) | D18: =MIN(B18*$E$4,$E$3) | E18: =D18*C18 | F18: =$B$4*Hypothèses!$B$11 | G18: =IF(A18=10,$B$4*Hypothèses!$D$19,0)+IF(A18=12,$B$4*Hypothèses!$D$18,0) | H18: =E18-F18-G18 | I18: =I17+H18 | J18: =IF(I18>=0,A18,9999)
A19: 6 | B19: =$B$3*Hypothèses!$B$5*(1-Hypothèses!$B$6)^(A19-1) | C19: =Hypothèses!$B$9*(1+Hypothèses!$B$10)^(A19-1) | D19: =MIN(B19*$E$4,$E$3) | E19: =D19*C19 | F19: =$B$4*Hypothèses!$B$11 | G19: =IF(A19=10,$B$4*Hypothèses!$D$19,0)+IF(A19=12,$B$4*Hypothèses!$D$18,0) | H19: =E19-F19-G19 | I19: =I18+H19 | J19: =IF(I19>=0,A19,9999)
A20: 7 | B20: =$B$3*Hypothèses!$B$5*(1-Hypothèses!$B$6)^(A20-1) | C20: =Hypothèses!$B$9*(1+Hypothèses!$B$10)^(A20-1) | D20: =MIN(B20*$E$4,$E$3) | E20: =D20*C20 | F20: =$B$4*Hypothèses!$B$11 | G20: =IF(A20=10,$B$4*Hypothèses!$D$19,0)+IF(A20=12,$B$4*Hypothèses!$D$18,0) | H20: =E20-F20-G20 | I20: =I19+H20 | J20: =IF(I20>=0,A20,9999)
A21: 8 | B21: =$B$3*Hypothèses!$B$5*(1-Hypothèses!$B$6)^(A21-1) | C21: =Hypothèses!$B$9*(1+Hypothèses!$B$10)^(A21-1) | D21: =MIN(B21*$E$4,$E$3) | E21: =D21*C21 | F21: =$B$4*Hypothèses!$B$11 | G21: =IF(A21=10,$B$4*Hypothèses!$D$19,0)+IF(A21=12,$B$4*Hypothèses!$D$18,0) | H21: =E21-F21-G21 | I21: =I20+H21 | J21: =IF(I21>=0,A21,9999)
A22: 9 | B22: =$B$3*Hypothèses!$B$5*(1-Hypothèses!$B$6)^(A22-1) | C22: =Hypothèses!$B$9*(1+Hypothèses!$B$10)^(A22-1) | D22: =MIN(B22*$E$4,$E$3) | E22: =D22*C22 | F22: =$B$4*Hypothèses!$B$11 | G22: =IF(A22=10,$B$4*Hypothèses!$D$19,0)+IF(A22=12,$B$4*Hypothèses!$D$18,0) | H22: =E22-F22-G22 | I22: =I21+H22 | J22: =IF(I22>=0,A22,9999)
A23: 10 | B23: =$B$3*Hypothèses!$B$5*(1-Hypothèses!$B$6)^(A23-1) | C23: =Hypothèses!$B$9*(1+Hypothèses!$B$10)^(A23-1) | D23: =MIN(B23*$E$4,$E$3) | E23: =D23*C23 | F23: =$B$4*Hypothèses!$B$11 | G23: =IF(A23=10,$B$4*Hypothèses!$D$19,0)+IF(A23=12,$B$4*Hypothèses!$D$18,0) | H23: =E23-F23-G23 | I23: =I22+H23 | J23: =IF(I23>=0,A23,9999)
A24: 11 | B24: =$B$3*Hypothèses!$B$5*(1-Hypothèses!$B$6)^(A24-1) | C24: =Hypothèses!$B$9*(1+Hypothèses!$B$10)^(A24-1) | D24: =MIN(B24*$E$4,$E$3) | E24: =D24*C24 | F24: =$B$4*Hypothèses!$B$11 | G24: =IF(A24=10,$B$4*Hypothèses!$D$19,0)+IF(A24=12,$B$4*Hypothèses!$D$18,0) | H24: =E24-F24-G24 | I24: =I23+H24 | J24: =IF(I24>=0,A24,9999)
A25: 12 | B25: =$B$3*Hypothèses!$B$5*(1-Hypothèses!$B$6)^(A25-1) | C25: =Hypothèses!$B$9*(1+Hypothèses!$B$10)^(A25-1) | D25: =MIN(B25*$E$4,$E$3) | E25: =D25*C25 | F25: =$B$4*Hypothèses!$B$11 | G25: =IF(A25=10,$B$4*Hypothèses!$D$19,0)+IF(A25=12,$B$4*Hypothèses!$D$18,0) | H25: =E25-F25-G25 | I25: =I24+H25 | J25: =IF(I25>=0,A25,9999)
... A38: 25 | B38: =$B$3*Hypothèses!$B$5*(1-Hypothèses!$B$6)^(A38-1) | C38: =Hypothèses!$B$9*(1+Hypothèses!$B$10)^(A38-1) | D38: =MIN(B38*$E$4,$E$3) | E38: =D38*C38 | F38: =$B$4*Hypothèses!$B$11 | G38: =IF(A38=10,$B$4*Hypothèses!$D$19,0)+IF(A38=12,$B$4*Hypothèses!$D$18,0) | H38: =E38-F38-G38 | I38: =I37+H38 | J38: =IF(I38>=0,A38,9999)

Sheet Sensibilité
A1: Sensibilité du payback — Config B1 (injection directe)
A2: Payback brut (années) selon le tarif électricité (lignes) et le coût du kWc (colonnes).
A4: Tarif \ Coût | B4: 600000 | C4: 700000 | D4: 800000 | E4: 900000
A5: 60 | B5: =IFERROR(('Cas client'!$B$13*B$4)/((MIN(('Cas client'!$B$13*Hypothèses!$B$5)*Hypothèses!$B$17,'Cas client'!$B$11)*$A5)-(('Cas client'!$B$13*B$4)*Hypothèses!$B$11)),"n/a") | C5: =IFERROR(('Cas client'!$B$13*C$4)/((MIN(('Cas client'!$B$13*Hypothèses!$B$5)*Hypothèses!$B$17,'Cas client'!$B$11)*$A5)-(('Cas client'!$B$13*C$4)*Hypothèses!$B$11)),"n/a") | D5: =IFERROR(('Cas client'!$B$13*D$4)/((MIN(('Cas client'!$B$13*Hypothèses!$B$5)*Hypothèses!$B$17,'Cas client'!$B$11)*$A5)-(('Cas client'!$B$13*D$4)*Hypothèses!$B$11)),"n/a") | E5: =IFERROR(('Cas client'!$B$13*E$4)/((MIN(('Cas client'!$B$13*Hypothèses!$B$5)*Hypothèses!$B$17,'Cas client'!$B$11)*$A5)-(('Cas client'!$B$13*E$4)*Hypothèses!$B$11)),"n/a")
A6: 70 | B6: =IFERROR(('Cas client'!$B$13*B$4)/((MIN(('Cas client'!$B$13*Hypothèses!$B$5)*Hypothèses!$B$17,'Cas client'!$B$11)*$A6)-(('Cas client'!$B$13*B$4)*Hypothèses!$B$11)),"n/a") | C6: =IFERROR(('Cas client'!$B$13*C$4)/((MIN(('Cas client'!$B$13*Hypothèses!$B$5)*Hypothèses!$B$17,'Cas client'!$B$11)*$A6)-(('Cas client'!$B$13*C$4)*Hypothèses!$B$11)),"n/a") | D6: =IFERROR(('Cas client'!$B$13*D$4)/((MIN(('Cas client'!$B$13*Hypothèses!$B$5)*Hypothèses!$B$17,'Cas client'!$B$11)*$A6)-(('Cas client'!$B$13*D$4)*Hypothèses!$B$11)),"n/a") | E6: =IFERROR(('Cas client'!$B$13*E$4)/((MIN(('Cas client'!$B$13*Hypothèses!$B$5)*Hypothèses!$B$17,'Cas client'!$B$11)*$A6)-(('Cas client'!$B$13*E$4)*Hypothèses!$B$11)),"n/a")
A7: 80 | B7: =IFERROR(('Cas client'!$B$13*B$4)/((MIN(('Cas client'!$B$13*Hypothèses!$B$5)*Hypothèses!$B$17,'Cas client'!$B$11)*$A7)-(('Cas client'!$B$13*B$4)*Hypothèses!$B$11)),"n/a") | C7: =IFERROR(('Cas client'!$B$13*C$4)/((MIN(('Cas client'!$B$13*Hypothèses!$B$5)*Hypothèses!$B$17,'Cas client'!$B$11)*$A7)-(('Cas client'!$B$13*C$4)*Hypothèses!$B$11)),"n/a") | D7: =IFERROR(('Cas client'!$B$13*D$4)/((MIN(('Cas client'!$B$13*Hypothèses!$B$5)*Hypothèses!$B$17,'Cas client'!$B$11)*$A7)-(('Cas client'!$B$13*D$4)*Hypothèses!$B$11)),"n/a") | E7: =IFERROR(('Cas client'!$B$13*E$4)/((MIN(('Cas client'!$B$13*Hypothèses!$B$5)*Hypothèses!$B$17,'Cas client'!$B$11)*$A7)-(('Cas client'!$B$13*E$4)*Hypothèses!$B$11)),"n/a")
A8: 90 | B8: =IFERROR(('Cas client'!$B$13*B$4)/((MIN(('Cas client'!$B$13*Hypothèses!$B$5)*Hypothèses!$B$17,'Cas client'!$B$11)*$A8)-(('Cas client'!$B$13*B$4)*Hypothèses!$B$11)),"n/a") | C8: =IFERROR(('Cas client'!$B$13*C$4)/((MIN(('Cas client'!$B$13*Hypothèses!$B$5)*Hypothèses!$B$17,'Cas client'!$B$11)*$A8)-(('Cas client'!$B$13*C$4)*Hypothèses!$B$11)),"n/a") | D8: =IFERROR(('Cas client'!$B$13*D$4)/((MIN(('Cas client'!$B$13*Hypothèses!$B$5)*Hypothèses!$B$17,'Cas client'!$B$11)*$A8)-(('Cas client'!$B$13*D$4)*Hypothèses!$B$11)),"n/a") | E8: =IFERROR(('Cas client'!$B$13*E$4)/((MIN(('Cas client'!$B$13*Hypothèses!$B$5)*Hypothèses!$B$17,'Cas client'!$B$11)*$A8)-(('Cas client'!$B$13*E$4)*Hypothèses!$B$11)),"n/a")
A9: 100 | B9: =IFERROR(('Cas client'!$B$13*B$4)/((MIN(('Cas client'!$B$13*Hypothèses!$B$5)*Hypothèses!$B$17,'Cas client'!$B$11)*$A9)-(('Cas client'!$B$13*B$4)*Hypothèses!$B$11)),"n/a") | C9: =IFERROR(('Cas client'!$B$13*C$4)/((MIN(('Cas client'!$B$13*Hypothèses!$B$5)*Hypothèses!$B$17,'Cas client'!$B$11)*$A9)-(('Cas client'!$B$13*C$4)*Hypothèses!$B$11)),"n/a") | D9: =IFERROR(('Cas client'!$B$13*D$4)/((MIN(('Cas client'!$B$13*Hypothèses!$B$5)*Hypothèses!$B$17,'Cas client'!$B$11)*$A9)-(('Cas client'!$B$13*D$4)*Hypothèses!$B$11)),"n/a") | E9: =IFERROR(('Cas client'!$B$13*E$4)/((MIN(('Cas client'!$B$13*Hypothèses!$B$5)*Hypothèses!$B$17,'Cas client'!$B$11)*$A9)-(('Cas client'!$B$13*E$4)*Hypothèses!$B$11)),"n/a")
A10: 110 | B10: =IFERROR(('Cas client'!$B$13*B$4)/((MIN(('Cas client'!$B$13*Hypothèses!$B$5)*Hypothèses!$B$17,'Cas client'!$B$11)*$A10)-(('Cas client'!$B$13*B$4)*Hypothèses!$B$11)),"n/a") | C10: =IFERROR(('Cas client'!$B$13*C$4)/((MIN(('Cas client'!$B$13*Hypothèses!$B$5)*Hypothèses!$B$17,'Cas client'!$B$11)*$A10)-(('Cas client'!$B$13*C$4)*Hypothèses!$B$11)),"n/a") | D10: =IFERROR(('Cas client'!$B$13*D$4)/((MIN(('Cas client'!$B$13*Hypothèses!$B$5)*Hypothèses!$B$17,'Cas client'!$B$11)*$A10)-(('Cas client'!$B$13*D$4)*Hypothèses!$B$11)),"n/a") | E10: =IFERROR(('Cas client'!$B$13*E$4)/((MIN(('Cas client'!$B$13*Hypothèses!$B$5)*Hypothèses!$B$17,'Cas client'!$B$11)*$A10)-(('Cas client'!$B$13*E$4)*Hypothèses!$B$11)),"n/a")
A11: 120 | B11: =IFERROR(('Cas client'!$B$13*B$4)/((MIN(('Cas client'!$B$13*Hypothèses!$B$5)*Hypothèses!$B$17,'Cas client'!$B$11)*$A11)-(('Cas client'!$B$13*B$4)*Hypothèses!$B$11)),"n/a") | C11: =IFERROR(('Cas client'!$B$13*C$4)/((MIN(('Cas client'!$B$13*Hypothèses!$B$5)*Hypothèses!$B$17,'Cas client'!$B$11)*$A11)-(('Cas client'!$B$13*C$4)*Hypothèses!$B$11)),"n/a") | D11: =IFERROR(('Cas client'!$B$13*D$4)/((MIN(('Cas client'!$B$13*Hypothèses!$B$5)*Hypothèses!$B$17,'Cas client'!$B$11)*$A11)-(('Cas client'!$B$13*D$4)*Hypothèses!$B$11)),"n/a") | E11: =IFERROR(('Cas client'!$B$13*E$4)/((MIN(('Cas client'!$B$13*Hypothèses!$B$5)*Hypothèses!$B$17,'Cas client'!$B$11)*$A11)-(('Cas client'!$B$13*E$4)*Hypothèses!$B$11)),"n/a")
A13: Colonnes = coût unitaire (FCFA/kWc) · Lignes = tarif évité (FCFA/kWh). Plus le tarif monte / le coût baisse, plus le retour est rapide.
